Metadata-Version: 1.0
Name: portopy
Version: 2.11.1
Summary: Python API for porto
Home-page: https://github.com/yandex/porto
Author: marchael
Author-email: marchael@yandex-team.ru
License: none
Platform: UNKNOWN
